setup.py
BBQSQL.egg-info/PKG-INFO
BBQSQL.egg-info/SOURCES.txt
BBQSQL.egg-info/dependency_links.txt
BBQSQL.egg-info/requires.txt
BBQSQL.egg-info/top_level.txt
bbqsql/__init__.py
bbqsql/settings.py
bbqsql/utilities.py
bbqsql/lib/__init__.py
bbqsql/lib/api.py
bbqsql/lib/pretty_print.py
bbqsql/lib/query.py
bbqsql/lib/requester.py
bbqsql/lib/technique.py
bbqsql/menu/__init__.py
bbqsql/menu/bbq_core.py
bbqsql/menu/bbq_menu.py
bbqsql/menu/config.py
bbqsql/menu/text.py
scripts/bbqsql