Metadata-Version: 1.0
Name: BBQSQL
Version: 1.0
Summary: Rapid Blind SQL Injection Exploitation Tool
Home-page: UNKNOWN
Author: Ben Toews (mastahyeti)
Author-email: mastahyeti@gmail.com
License: BSD
Platform: UNKNOWN
